{
  "_id": "s8A8GKMsAKYKa0gg",
  "name": "ALL-SEEING EYE",
  "type": "feat",
  "img": "icons/magic/perception/eye-ringed-green.webp",
  "_stats": {
    "coreVersion": "13.350",
    "systemId": "pf1",
    "systemVersion": "11.11",
    "createdTime": null,
    "modifiedTime": null,
    "lastModifiedBy": null
  },
  "system": {
    "subType": "feat",
    "abilityType": "ex",
    "description": {
      "value": "<p><b>Prerequisite:</b> Advanced Bloodline (Byakugan), Byakugan Sight, Byakugan +3, Keen Sight +4.</p>\n<p><b>Benefit:</b> Up to three times per day, while Byakugan is active, you can spend a swift action to gain Blindsense with a range up to 30 feet for 1 round. The Blindsense is lost if you become blinded.</p>",
      "summary": "Up to three times per day, while Byakugan is active, you can spend a swift action to gain Blindsense with a range up…",
      "instructions": ""
    },
    "tags": [],
    "disabled": false,
    "changes": [],
    "links": {
      "prerequisites": [],
      "supplements": [],
      "children": []
    },
    "actions": [],
    "scriptCalls": [],
    "flags": {
      "boolean": {},
      "dictionary": {}
    },
    "showInQuickbar": false,
    "showInCombat": false
  },
  "effects": [],
  "folder": "sIYCY0IyyIAy8mqI",
  "sort": 0,
  "ownership": {
    "default": 0
  },
  "flags": {
    "naruto-d20": {
      "discipline": "",
      "source": "Core Rulebook",
      "tags": [
        "Clan"
      ],
      "hasChanges": false,
      "activeEffect": true
    }
  },
  "_key": "!items!s8A8GKMsAKYKa0gg"
}
