{
  "_id": "1RLFSn1stpCaIxNf",
  "name": "SHINSUBU NO JUTSU (SOUL BINDING TECHNIQUE)",
  "type": "naruto-d20.technique",
  "img": "systems/pf1/icons/spells/link-blue-1.jpg",
  "_stats": {
    "coreVersion": "13.350",
    "systemId": "pf1",
    "systemVersion": "11.11",
    "createdTime": null,
    "modifiedTime": null,
    "lastModifiedBy": null
  },
  "system": {
    "description": {
      "value": "<p>The target must be bearing a child (of any type) and be within a day from going into labor or otherwise birthing it. You take the soul stored with the Katou Shin Fuuin technique, and transfer it from the object into the unborn child. The unborn child gains a bonus to a score modifier, up to +4. (For example, if the subject's highest ability score was 20 Constitution, the infant would gain a +4 bonus to Constitution; in case of a tie, single ability score based on the subject's highest ability determine at random).<br><br>In addition, the child gains any template or bloodline the subject has (except Moujuu Aishou), and has a 75% chance to gain the subject's primary allegiance as one of its own allegiances. The GM may decide to award additional effects or special templates depending on the subject (such as granting the Ghastly Inheritance template when sealing the Kyuubi's spirit). Upon child- birth, the creature that bore the child will die (no save). If the target succeeded at their save, the soul escapes and vanishes, allowing it to later be resurrected once again.</p>\n\n\n\n",
      "summary": "",
      "instructions": ""
    },
    "discipline": "Fuinjutsu",
    "subtype": "",
    "descriptors": [
      "Kinjutsu"
    ],
    "rank": 14,
    "complexity": "SS-Class",
    "chakraCost": 30,
    "activation": "hour",
    "range": "Melee Touch",
    "target": "One creature *",
    "area": "",
    "duration": "Permanent",
    "save": "Will negates",
    "compHandSeals": true,
    "compHalfSeals": false,
    "compConcentration": true,
    "compMobility": false,
    "compFocus": true,
    "compEmpower": false,
    "compMastery": false,
    "compPhysical": false,
    "compXpCost": true,
    "isHijutsu": false,
    "isKinjutsu": true,
    "isCombination": false,
    "performMiscBonus": 0,
    "active": false,
    "changes": [],
    "actions": [
      {
        "_id": "e9614c0a64708a5a",
        "name": "Use",
        "actionType": "save",
        "activation": {
          "type": "hour",
          "cost": 1,
          "unchained": {
            "type": "hour",
            "cost": 1
          }
        },
        "duration": {
          "units": "perm"
        },
        "range": {
          "units": "touch"
        },
        "target": {
          "value": "One creature *"
        },
        "save": {
          "type": "will",
          "description": "Will negates"
        }
      }
    ],
    "scriptCalls": [],
    "links": {
      "prerequisites": [],
      "supplements": [],
      "children": []
    },
    "tag": "",
    "tags": [],
    "flags": {
      "boolean": {},
      "dictionary": {}
    },
    "showInQuickbar": false,
    "showInCombat": false,
    "chakraResistance": true,
    "sources": [
      {
        "title": "NarutoD20 Redux v1.3",
        "pages": "264"
      }
    ],
    "automation": {
      "enabled": false
    }
  },
  "effects": [],
  "folder": "IyI6SaQ4YeCUiO6A",
  "sort": 0,
  "ownership": {
    "default": 0
  },
  "flags": {},
  "_key": "!items!1RLFSn1stpCaIxNf"
}
